python/__init__.py
pythonista-1.0.0.dist-info/LICENSE
pythonista-1.0.0.dist-info/METADATA
pythonista-1.0.0.dist-info/WHEEL
pythonista-1.0.0.dist-info/entry_points.txt
pythonista-1.0.0.dist-info/top_level.txt
pythonista-1.0.0.dist-info/RECORD
