Metadata-Version: 2.1
Name: pythonista
Version: 1.0.0
Summary: A shortcut command for Python
Home-page: https://github.com/cj-praveen/pythonista/
License-File: LICENSE
